[
  {
    "key": "901",
    "type": "invite",
    "status": "pending",
    "userid": "11",
    "email": "demo",
    "creatorId": "51",
    "context": {
      "view": {}
    },
    "token": "123dem"
  },
  {
    "key": "902",
    "type": "invite",
    "status": "pending",
    "email": "henry.clark@example.com",
    "creatorId": "51",
    "context": {
      "view": {}
    },
    "token": "123hen"
  },
  {
    "key": "903",
    "type": "invite",
    "status": "pending",
    "email": "gregory.jones@example.com",
    "creatorId": "11",
    "context": {
      "view": {}
    },
    "token": "123greg"
  }
]
